LICENSE
MANIFEST.in
README.md
requirements.txt
setup.cfg
setup.py
django_mp_tecdoc.egg-info/PKG-INFO
django_mp_tecdoc.egg-info/SOURCES.txt
django_mp_tecdoc.egg-info/dependency_links.txt
django_mp_tecdoc.egg-info/requires.txt
django_mp_tecdoc.egg-info/top_level.txt
tecdoc/__init__.py
tecdoc/admin.py
tecdoc/constants.py
tecdoc/filters.py
tecdoc/models.py
tecdoc/routers.py
tecdoc/urls.py
tecdoc/utils.py
tecdoc/views.py
tecdoc/locale/ru/LC_MESSAGES/django.mo
tecdoc/locale/ru/LC_MESSAGES/django.po
tecdoc/locale/uk/LC_MESSAGES/django.mo
tecdoc/locale/uk/LC_MESSAGES/django.po
tecdoc/templates/tecdoc/cell.html
tecdoc/templates/tecdoc/hint.html