Metadata-Version: 1.1
Name: django-mp-tecdoc
Version: 1.0.4
Summary: Django tecdoc app
Home-page: https://github.com/pmaigutyak/mp-tecdoc
Author: Paul Maigutyak
Author-email: pmaigutyak@gmail.com
License: MIT
Download-URL: https://github.com/pmaigutyak/mp-tecdoc/archive/1.0.4.tar.gz
Platform: UNKNOWN
